[
  {
    "title": "NLE Choppa Has Some Words for NBA YoungBoy on His New Single \u2018KO\u2019",
    "link": "https://www.rollingstone.com/music/music-news/nle-choppas-new-single-ko-1235456919/",
    "source": "Music News",
    "published": "Thu, 30 Oct 2025 23:37:03 +0000",
    "image": "https://www.rollingstone.com/wp-content/uploads/2025/10/NLE-Choppa-KO-single.jpg?w=1600&h=900&crop=1"
  },
  {
    "title": "Lily Allen Announces West End Girl UK Tour",
    "link": "https://www.stereogum.com/2328297/lily-allen-announces-west-end-girl-uk-tour/news/",
    "source": "Stereogum",
    "published": "Thu, 30 Oct 2025 23:13:29 +0000",
    "image": null
  },
  {
    "title": "Arcade Fire\u2019s Win Butler And R\u00e9gine Chassagne Are Separating",
    "link": "https://www.stereogum.com/2328293/arcade-fires-win-butler-and-regine-chassagne-are-separating/news/",
    "source": "Stereogum",
    "published": "Thu, 30 Oct 2025 22:23:05 +0000",
    "image": null
  },
  {
    "title": "7 New Songs Out Today",
    "link": "https://www.brooklynvegan.com/7-new-songs-out-today-37/",
    "source": "BrooklynVegan",
    "published": "Thu, 30 Oct 2025 21:58:23 +0000",
    "image": "https://media.brooklynvegan.com/xxrzsfjkyw/uploads/2025/10/30/crooked-man-cunts-video.jpg"
  },
  {
    "title": "BTS Fanfic Files \u2014 Halloween Edition: Podcast",
    "link": "https://consequence.net/2025/10/stanning-bts-fanfic-files-halloween-podcast/",
    "source": "Consequence",
    "published": "Thu, 30 Oct 2025 21:41:15 +0000",
    "image": "https://consequence.net/wp-content/uploads/2025/10/stanning-bts-halloween-podcast.jpg?quality=80"
  },
  {
    "title": "Arcade Fire\u2019s Win Butler and R\u00e9gine Chassagne Split After 22 Years of Marriage",
    "link": "https://www.rollingstone.com/music/music-news/arcade-fire-win-butler-regine-chassagne-marriage-separation-1235457274/",
    "source": "Music News",
    "published": "Thu, 30 Oct 2025 21:33:53 +0000",
    "image": "https://www.rollingstone.com/wp-content/uploads/2025/10/regine-chassagne-win-butler-split.jpg?crop=0px%2C83px%2C1800px%2C1014px&resize=1600%2C900"
  },
  {
    "title": "Sharon Stone Defends Sydney Sweeney: \u201cIt\u2019s Hard to Be Hot\u201d",
    "link": "https://consequence.net/2025/10/sharon-stone-sydney-sweeney-hard-to-be-hot/",
    "source": "Consequence",
    "published": "Thu, 30 Oct 2025 21:16:56 +0000",
    "image": "https://consequence.net/wp-content/uploads/2025/10/sharon-stone-sydney-sweeney-amer.jpeg?quality=80"
  },
  {
    "title": "Arcade Fire\u2019s  Win Butler and R\u00e9gine Chassagne Announce Separation",
    "link": "https://consequence.net/2025/10/arcade-fire-win-butler-regine-chassagne-announce-separation/",
    "source": "Consequence",
    "published": "Thu, 30 Oct 2025 21:11:05 +0000",
    "image": "https://consequence.net/wp-content/uploads/2025/10/Arcade-Fire.jpeg?quality=80"
  },
  {
    "title": "Kim Kardashian on Moon Landing: \u201cI Think It Was Fake\u201d",
    "link": "https://consequence.net/2025/10/kim-kardashian-moon-landing-fake-didnt-happen/",
    "source": "Consequence",
    "published": "Thu, 30 Oct 2025 20:50:04 +0000",
    "image": "https://consequence.net/wp-content/uploads/2025/10/Kim-Moon.jpeg?quality=80"
  },
  {
    "title": "Bon Jovi, the Offspring, Billy Idol, and More Remember Late Philly DJ Pierre Robert",
    "link": "https://www.rollingstone.com/music/music-news/pierre-robert-remembered-tributes-bon-jovi-the-offspring-1235457221/",
    "source": "Music News",
    "published": "Thu, 30 Oct 2025 20:50:03 +0000",
    "image": "https://www.rollingstone.com/wp-content/uploads/2025/10/GettyImages-117786879-2.jpg?w=1600&h=900&crop=1"
  },
  {
    "title": "Arcade Fire\u2019s Win Butler & R\u00e9gine Chassagne announce separation",
    "link": "https://www.brooklynvegan.com/arcade-fires-win-butler-regine-chassagne-announce-separation/",
    "source": "BrooklynVegan",
    "published": "Thu, 30 Oct 2025 20:46:09 +0000",
    "image": "https://media.brooklynvegan.com/xxrzsfjkyw/uploads/2017/08/25/arcadefire-metro-27.jpg"
  },
  {
    "title": "Arcade Fire\u2019s Win Butler and R\u00e9gine Chassagne Announce Separation",
    "link": "https://pitchfork.com/news/arcade-fire-win-butler-and-regine-chassagne-announce-separation",
    "source": "RSS: News",
    "published": "Thu, 30 Oct 2025 20:46:00 +0000",
    "image": "https://media.pitchfork.com/photos/6903cb26bbd9e89d8731b5c5/master/pass/Arcade-Fire.jpeg"
  },
  {
    "title": "Bugonia Is 2025\u2019s Most Frustrating Film",
    "link": "https://consequence.net/2025/10/bugonia-review-yorgos-lanthimos-emma-stone/",
    "source": "Consequence",
    "published": "Thu, 30 Oct 2025 20:34:49 +0000",
    "image": "https://consequence.net/wp-content/uploads/2025/10/bugonia-emma-stone-2.jpg?quality=80"
  },
  {
    "title": "Febuary, Silk, Krylon & Risk Yo Life playing NYC benefit for Danny Evans (OLTH, Cash Only Tonys)",
    "link": "https://www.brooklynvegan.com/febuary-silk-krylon-risk-yo-life-playing-nyc-benefit-for-danny-evans-olth-cash-only-tonys/",
    "source": "BrooklynVegan",
    "published": "Thu, 30 Oct 2025 20:11:05 +0000",
    "image": "https://media.brooklynvegan.com/xxrzsfjkyw/uploads/2025/10/30/febuary.jpg"
  },
  {
    "title": "Sean Combs Transferred to Federal Prison to Serve Sentence",
    "link": "https://www.rollingstone.com/music/music-news/sean-diddy-combs-prison-fort-dix-new-jersey-1235441834/",
    "source": "Music News",
    "published": "Thu, 30 Oct 2025 20:03:45 +0000",
    "image": "https://www.rollingstone.com/wp-content/uploads/2025/10/diddy-prison-assignment.jpg?w=1600&h=900&crop=1"
  },
  {
    "title": "Alice Cooper and Criss Angel Teaming Up for \u201cWelcome to Our Nightmare\u201d Las Vegas Show",
    "link": "https://consequence.net/2025/10/alice-cooper-criss-angel-welcome-to-our-nightmare-las-vegas/",
    "source": "Consequence",
    "published": "Thu, 30 Oct 2025 20:03:07 +0000",
    "image": "https://consequence.net/wp-content/uploads/2025/10/Welcome-to-Our-Nightmare.jpg?quality=80"
  },
  {
    "title": "Hole Bassist Melissa Auf der Maur Announces New Memoir",
    "link": "https://pitchfork.com/news/hole-bassist-melissa-auf-der-maur-announces-new-memoir",
    "source": "RSS: News",
    "published": "Thu, 30 Oct 2025 19:54:38 +0000",
    "image": "https://media.pitchfork.com/photos/6903b7f6e663ba293a48553a/master/pass/Melissa-Auf-der-Maur.jpeg"
  },
  {
    "title": "Dave Mustaine Reclaims Metallica\u2019s \u201cRide The Lightning\u201d For Final Megadeth Album",
    "link": "https://www.stereogum.com/2328277/dave-mustaine-reclaims-metallicas-ride-the-lightning-for-final-megadeth-album/news/",
    "source": "Stereogum",
    "published": "Thu, 30 Oct 2025 19:15:32 +0000",
    "image": null
  },
  {
    "title": "Mining Metal: Dwelling Below, Lammoth/Gonemage, Lucerne Hammer, Morke, The Munsens, Silent Tombs, Terzij de Horde, and Void of Sleep",
    "link": "https://consequence.net/2025/10/mining-metal-october-2025/",
    "source": "Consequence",
    "published": "Thu, 30 Oct 2025 18:41:14 +0000",
    "image": "https://consequence.net/wp-content/uploads/2025/10/MM-October-2025-FB.jpg?quality=80"
  },
  {
    "title": "Twenty One Pilots To Perform \u201cSeven Nation Army\u201d At Rock & Roll Hall Of Fame Induction Ceremony",
    "link": "https://www.stereogum.com/2328271/twenty-one-pilots-to-perform-seven-nation-army-at-rock-roll-hall-of-fame-induction-ceremony/news/",
    "source": "Stereogum",
    "published": "Thu, 30 Oct 2025 18:20:29 +0000",
    "image": null
  },
  {
    "title": "Twenty One Pilots to Perform The White Stripes\u2019 \u201cSeven Nation Army\u201d at Rock & Roll Hall of Fame Ceremony",
    "link": "https://consequence.net/2025/10/twenty-one-pilots-to-perform-the-white-stripes-seven-nation-army-at-rock-roll-hall-of-fame-ceremony/",
    "source": "Consequence",
    "published": "Thu, 30 Oct 2025 18:19:08 +0000",
    "image": "https://consequence.net/wp-content/uploads/2025/10/Twenty-One-Pilots-White-Stripes.jpg?quality=80"
  },
  {
    "title": "Oasis Box Up \u2018Morning Glory\u2019 Singles, \u2018Wonderwall\u2019 Turns 30",
    "link": "https://www.spin.com/2025/10/oasis-morning-gloy-singles/",
    "source": "SPIN",
    "published": "Thu, 30 Oct 2025 18:06:00 +0000",
    "image": "https://static.spin.com/files/2025/09/1C3A4216-Enhanced-NR-MEXICO-N2-HARRIETTKBOLS-Oasis-Instagram-Export-5-scaled.jpg"
  },
  {
    "title": "Melissa Auf Der Maur Looks Back With \u2018Good\u2019 Memoir",
    "link": "https://www.spin.com/2025/10/melissa-auf-der-maur-memoir/",
    "source": "SPIN",
    "published": "Thu, 30 Oct 2025 18:05:00 +0000",
    "image": "https://static.spin.com/files/2004/05/GettyImages-142488176-1486411950.jpg"
  },
  {
    "title": "King of the Hill Renewed for Two More Seasons",
    "link": "https://consequence.net/2025/10/king-of-the-hill-season-16-17-hulu/",
    "source": "Consequence",
    "published": "Thu, 30 Oct 2025 18:02:11 +0000",
    "image": "https://consequence.net/wp-content/uploads/2025/10/king-of-the-hill-season-14.jpg?quality=80"
  },
  {
    "title": "Taylor Sheridan\u00a0Developing Live-Action Call of Duty Movie",
    "link": "https://consequence.net/2025/10/taylor-sheridan-call-of-duty-movie-paramount/",
    "source": "Consequence",
    "published": "Thu, 30 Oct 2025 18:01:19 +0000",
    "image": "https://consequence.net/wp-content/uploads/2025/10/taylor-sheridan-call-of-duty-movie.jpg?quality=80"
  },
  {
    "title": "Brandi Carlile Returns to Herself",
    "link": "https://www.spin.com/2025/10/brandi-carlile-returns-to-herself/",
    "source": "SPIN",
    "published": "Thu, 30 Oct 2025 18:00:00 +0000",
    "image": "https://static.spin.com/files/2025/10/brandi_carlile_2Collier-Schorr-e1761830134258.jpg"
  },
  {
    "title": "Blondie\u2019s Debby Harry & Chris Stein talk upcoming album, musical inspirations, more in new interview",
    "link": "https://www.brooklynvegan.com/blondies-debby-harry-chris-stein-talk-upcoming-album-musical-inspirations-more-in-new-interview/",
    "source": "BrooklynVegan",
    "published": "Thu, 30 Oct 2025 17:43:17 +0000",
    "image": "https://media.brooklynvegan.com/xxrzsfjkyw/uploads/2025/10/30/blondie-getty.jpg"
  },
  {
    "title": "Hole & Smashing Pumpkins Bassist Melissa Auf der Maur Announces \u201c\u201990s Rock Memoir\u201d Even The Good Girls Will Cry",
    "link": "https://www.stereogum.com/2328246/hole-smashing-pumpkins-bassist-melissa-auf-der-maur-announces-90s-rock-memoir-even-the-good-girls-will-cry/news/",
    "source": "Stereogum",
    "published": "Thu, 30 Oct 2025 17:36:49 +0000",
    "image": null
  },
  {
    "title": "The Weather Station \u2013 \u201cAirport\u201d & \u201cOnly The Truth\u201d",
    "link": "https://www.stereogum.com/2328262/the-weather-station-airport-only-the-truth/music/",
    "source": "Stereogum",
    "published": "Thu, 30 Oct 2025 17:07:28 +0000",
    "image": null
  },
  {
    "title": "Questlove Writes Tribute To His Late Friend And Collaborator D\u2019Angelo",
    "link": "https://www.stereogum.com/2328232/questlove-writes-tribute-to-his-late-friend-and-collaborator-dangelo/news/",
    "source": "Stereogum",
    "published": "Thu, 30 Oct 2025 16:55:10 +0000",
    "image": null
  },
  {
    "title": "Pulp\u2019s \u2018Different Class\u2019 at 30 remains a masterpiece of misshapes, mistakes & misfits",
    "link": "https://www.brooklynvegan.com/pulps-different-class-at-30-remains-a-masterpiece-of-misshapess-mistakes-misfits/",
    "source": "BrooklynVegan",
    "published": "Thu, 30 Oct 2025 16:10:08 +0000",
    "image": "https://media.brooklynvegan.com/xxrzsfjkyw/uploads/2020/11/22/Pulp-Different-Class.jpg"
  },
  {
    "title": "New exclusive vinyl: blink-182/Swindle\u2019s \u2018Lemmings\u2019 split on splatter 7\u2033",
    "link": "https://www.brooklynvegan.com/new-exclusive-vinyl-blink-182-swindles-lemmings-split-on-splatter-7/",
    "source": "BrooklynVegan",
    "published": "Thu, 30 Oct 2025 16:00:15 +0000",
    "image": "https://media.brooklynvegan.com/xxrzsfjkyw/uploads/2025/10/30/blink182-vinylart.jpg"
  },
  {
    "title": "Mk.gee & Matty Healy Join Dijon Onstage In LA",
    "link": "https://www.stereogum.com/2328238/mk-gee-matty-healy-join-dijon-onstage-in-la/news/",
    "source": "Stereogum",
    "published": "Thu, 30 Oct 2025 15:26:32 +0000",
    "image": null
  },
  {
    "title": "There Are No Rap Songs In The Top 40 For The First Time In 35 Years",
    "link": "https://www.stereogum.com/2328218/there-are-no-rap-songs-in-the-top-40-for-the-first-time-in-35-years/columns/sounding-board/",
    "source": "Stereogum",
    "published": "Thu, 30 Oct 2025 15:03:19 +0000",
    "image": null
  },
  {
    "title": "Watch the New Trailer for Stranger Things\u2019 Final Season",
    "link": "https://pitchfork.com/news/watch-the-new-trailer-for-stranger-things-final-season",
    "source": "RSS: News",
    "published": "Thu, 30 Oct 2025 14:45:58 +0000",
    "image": "https://media.pitchfork.com/photos/6903869463c5d07d6decaeb3/master/pass/Stranger-Things-5.jpeg"
  },
  {
    "title": "Lily Allen Announces UK Tour for West End Girl",
    "link": "https://pitchfork.com/news/lily-allen-announces-uk-tour-for-west-end-girl",
    "source": "RSS: News",
    "published": "Thu, 30 Oct 2025 14:17:14 +0000",
    "image": "https://media.pitchfork.com/photos/69037257dbfb532e8f814d2f/master/pass/Lily-Allen-2025.jpeg"
  },
  {
    "title": "Gary Numan Shares Previously Unreleased 1980 Track \u201cLike A B-Film\u201d From New Telekon Reissue",
    "link": "https://www.stereogum.com/2328221/gary-numan-shares-previously-unreleased-1980-track-like-a-b-film-from-new-telekon-reissue/music/",
    "source": "Stereogum",
    "published": "Thu, 30 Oct 2025 14:16:20 +0000",
    "image": null
  },
  {
    "title": "5 Artists from A Diamond Heart Production You Need to Know Right Now",
    "link": "https://www.spin.com/2025/10/5-artists-from-a-diamond-heart-production-you-need-to-know-right-now/",
    "source": "SPIN",
    "published": "Thu, 30 Oct 2025 13:55:02 +0000",
    "image": "https://static.spin.com/files/2025/10/Vanessa-Silberman-by-Michelle-LoBianco-1-scaled.jpg"
  },
  {
    "title": "Listen to Lankum\u2019s amazing cover of The Specials\u2019 \u201cGhost Town\u201d",
    "link": "https://www.brooklynvegan.com/listen-to-lankums-amazing-cover-of-the-specials-ghost-town/",
    "source": "BrooklynVegan",
    "published": "Thu, 30 Oct 2025 13:50:39 +0000",
    "image": "https://media.brooklynvegan.com/xxrzsfjkyw/uploads/2025/10/30/lankum-ghost-town.jpg"
  },
  {
    "title": "Stream NJ screamo band Massa Nera\u2019s new album \u2018The Emptiness of All Things\u2019",
    "link": "https://www.brooklynvegan.com/stream-nj-screamo-band-massa-neras-new-album-the-emptiness-of-all-things/",
    "source": "BrooklynVegan",
    "published": "Thu, 30 Oct 2025 13:27:26 +0000",
    "image": "https://media.brooklynvegan.com/xxrzsfjkyw/uploads/2025/08/28/Massa-Nera-Emptiness-of-All-Things-copy.jpg"
  },
  {
    "title": "Dance Hall Crashers\u2019 NYC reunion shows with Hepcat on BV Presale (password here)",
    "link": "https://www.brooklynvegan.com/dance-hall-crashers-nyc-reunion-shows-with-hepcat-on-bv-presale-password-here/",
    "source": "BrooklynVegan",
    "published": "Thu, 30 Oct 2025 13:17:18 +0000",
    "image": "https://media.brooklynvegan.com/xxrzsfjkyw/uploads/2025/09/22/003-Dance-Hall-Crashers-011.jpg"
  },
  {
    "title": "Listen to Saba\u2019s New Project C0ffee!",
    "link": "https://pitchfork.com/news/listen-to-saba-new-project-c0ffee",
    "source": "RSS: News",
    "published": "Thu, 30 Oct 2025 13:16:20 +0000",
    "image": "https://media.pitchfork.com/photos/69036491fe46ca51a87f821f/master/pass/Saba.jpg"
  },
  {
    "title": "Lankum \u2013 \u201cGhost Town\u201d (The Specials Cover)",
    "link": "https://www.stereogum.com/2328209/lankum-ghost-town-the-specials-cover/music/",
    "source": "Stereogum",
    "published": "Thu, 30 Oct 2025 12:50:14 +0000",
    "image": null
  },
  {
    "title": "Oklou Shares Three New Songs On Choke Enough Deluxe, Plays Tiny Desk Concert",
    "link": "https://www.stereogum.com/2328212/oklou-shares-three-new-songs-on-choke-enough-deluxe-plays-tiny-desk-concert/music/",
    "source": "Stereogum",
    "published": "Thu, 30 Oct 2025 12:50:04 +0000",
    "image": null
  },
  {
    "title": "Ken Carson Summons Halloween Chaos With \u2018Yes\u2019: Stream It\u00a0Now",
    "link": "https://www.billboard.com/music/rb-hip-hop/ken-carson-single-yes-1236102409/",
    "source": "Billboard",
    "published": "Fri, 31 Oct 2025 06:39:35 +0000",
    "image": null
  },
  {
    "title": "Offset Drops Surprise Halloween Album \u2018Haunted by Fame\u2019: Stream It\u00a0Now",
    "link": "https://www.billboard.com/music/rb-hip-hop/offset-haunted-by-fame-album-stream-1236102404/",
    "source": "Billboard",
    "published": "Fri, 31 Oct 2025 06:00:31 +0000",
    "image": null
  },
  {
    "title": "11 New Albums You Should Listen to Now: Snocaps, Florence and the Machine, and More",
    "link": "https://pitchfork.com/news/11-new-albums-you-should-listen-to-now-snocaps-florence-and-the-machine",
    "source": "RSS: News",
    "published": "Fri, 31 Oct 2025 04:10:41 +0000",
    "image": "https://media.pitchfork.com/photos/6903a614a50b582766f33cc1/master/pass/Snocaps.jpeg"
  },
  {
    "title": "Katie and Allison Crutchfield Reunite, Drop Surprise New Album Under the Name Snocaps",
    "link": "https://www.rollingstone.com/music/music-news/snocaps-surprise-album-crutchfield-sisters-1235457115/",
    "source": "Music News",
    "published": "Fri, 31 Oct 2025 04:08:52 +0000",
    "image": "https://www.rollingstone.com/wp-content/uploads/2025/10/Snocaps-Photo-by-Chris-Black.jpg?w=1600&h=900&crop=1"
  },
  {
    "title": "Katie & Allison Crutchfield, MJ Lenderman, & Brad Cook Are Snocaps \u2014 Hear Their Surprise Debut Album",
    "link": "https://www.stereogum.com/2328283/katie-allison-crutchfield-mj-lenderman-brad-cook-are-snocaps-hear-their-surprise-debut-album/music/",
    "source": "Stereogum",
    "published": "Fri, 31 Oct 2025 04:00:59 +0000",
    "image": null
  },
  {
    "title": "Florence + the Machine Bring Brutal Honesty and Cathartic Transformations to Everybody Scream: Review",
    "link": "https://consequence.net/2025/10/florence-and-the-machine-everybody-scream-album-review/",
    "source": "Consequence",
    "published": "Fri, 31 Oct 2025 04:00:21 +0000",
    "image": "https://consequence.net/wp-content/uploads/2025/10/Florence-the-Machine-Everybody-Scream-Review.jpg?quality=80"
  },
  {
    "title": "Florence + The Machine Cover Lady Gaga\u2019s \u201cAbracadabra\u201d: Watch",
    "link": "https://consequence.net/2025/10/florence-the-machine-cover-lady-gaga-abracadabra/",
    "source": "Consequence",
    "published": "Fri, 31 Oct 2025 03:00:51 +0000",
    "image": "https://consequence.net/wp-content/uploads/2025/10/Florence-The-Machine-Abracadabra-SiriusXM.jpg?quality=80"
  },
  {
    "title": "Florence and the Machine Perform Witchy Rendition of Lady Gaga\u2019s \u2018Abracadabra\u2019",
    "link": "https://www.rollingstone.com/music/music-news/florence-and-the-machine-lady-gaga-abracadabra-cover-1235457442/",
    "source": "Music News",
    "published": "Fri, 31 Oct 2025 01:10:28 +0000",
    "image": "https://www.rollingstone.com/wp-content/uploads/2025/10/florence-gaga.jpg?w=1600&h=900&crop=1"
  },
  {
    "title": "Watch Florence Road Cover Phoebe Bridgers For Like A Version",
    "link": "https://www.stereogum.com/2328307/watch-florence-road-cover-phoebe-bridgers-for-like-a-version/news/",
    "source": "Stereogum",
    "published": "Fri, 31 Oct 2025 00:53:27 +0000",
    "image": null
  },
  {
    "title": "Oklou Shares New Choke Enough (Deluxe) Songs: Listen",
    "link": "https://pitchfork.com/news/oklou-shares-new-choke-enough-deluxe-songs-listen",
    "source": "RSS: News",
    "published": "Fri, 31 Oct 2025 00:26:41 +0000",
    "image": "https://media.pitchfork.com/photos/6903c53fb4a0a97de514ebd6/master/pass/Oklou.jpeg"
  },
  {
    "title": "Demi Lovato Frees\u00a0Meme Twin\u00a0Poot From Her Basement\u00a0to Celebrate New Album",
    "link": "https://www.rollingstone.com/music/music-news/demi-lovato-dresses-meme-poot-halloween-new-album-1235457423/",
    "source": "Music News",
    "published": "Fri, 31 Oct 2025 00:13:13 +0000",
    "image": "https://www.rollingstone.com/wp-content/uploads/2025/10/poot-lovato-freed.jpg?w=1600&h=900&crop=1"
  }
]