[
  {
    "title": "Watch Jelly Roll Perform Power Ballad About His Online Haters",
    "link": "https://www.rollingstone.com/music/music-news/jelly-roll-power-ballad-online-haters-kimmel-1235401582/",
    "source": "Music News",
    "published": "Wed, 06 Aug 2025 06:59:37 +0000",
    "image": "https://www.rollingstone.com/wp-content/uploads/2025/08/GettyImages-2224956787.jpg?w=1600&h=900&crop=1"
  },
  {
    "title": "Kendrick Lamar Adds New Australian Shows With Doechii as\u00a0Support",
    "link": "https://www.billboard.com/music/rb-hip-hop/kendrick-lamar-adds-extra-melbourne-amp-sydney-shows-doechii-support-1236037651/",
    "source": "Billboard",
    "published": "Wed, 06 Aug 2025 06:46:53 +0000",
    "image": "https://www.billboard.com/wp-content/uploads/2025/08/kendrick-lamar-super-bowl-2025-billboard-1800.jpg?w=1024"
  },
  {
    "title": "Avalon Penrose\u2019s Operatic \u2018AGT\u2019 Audition Descends Into Messy\u00a0Mayhem",
    "link": "https://www.billboard.com/music/music-news/avalon-penrose-operatic-agt-audition-messy-mayhem-1236037647/",
    "source": "Billboard",
    "published": "Wed, 06 Aug 2025 05:56:15 +0000",
    "image": "https://www.billboard.com/wp-content/uploads/2025/08/avalon-penrose-agt-americas-got-talent-2025-billboard-1548.jpg?w=1024"
  },
  {
    "title": "Sony Music Sues Napster Over Missed Royalty Payments",
    "link": "https://pitchfork.com/news/sony-music-sues-napster-over-missed-royalty-payments",
    "source": "RSS: News",
    "published": "Wed, 06 Aug 2025 03:21:08 +0000",
    "image": "https://media.pitchfork.com/photos/6892c9c8f2a41d64a8115cc6/master/pass/Napster.jpeg"
  },
  {
    "title": "South Park Trolls Department of Homeland of Security for Using Image of Show to Promote Ice",
    "link": "https://consequence.net/2025/08/south-park-responds-department-of-homeland-security/",
    "source": "Consequence",
    "published": "Wed, 06 Aug 2025 01:53:06 +0000",
    "image": "https://consequence.net/wp-content/uploads/2025/08/south-park.jpg?quality=80"
  },
  {
    "title": "Field Medic \u2013 \u201csimply obsessed\u201d",
    "link": "https://www.stereogum.com/2318322/field-medic-simply-obsessed/music/",
    "source": "Stereogum",
    "published": "Wed, 06 Aug 2025 01:31:41 +0000",
    "image": null
  },
  {
    "title": "Low Girl \u2013 \u201cNo Reasons\u201d",
    "link": "https://www.stereogum.com/2318318/low-girl-no-reasons/music/",
    "source": "Stereogum",
    "published": "Wed, 06 Aug 2025 01:15:37 +0000",
    "image": null
  },
  {
    "title": "dust Announce Debut Album Sky Is Falling: Hear \u201cDrawbacks\u201d",
    "link": "https://www.stereogum.com/2318313/dust-announce-debut-album-sky-is-falling-hear-drawbacks/music/",
    "source": "Stereogum",
    "published": "Wed, 06 Aug 2025 00:39:13 +0000",
    "image": null
  },
  {
    "title": "John Mayer Celebrates Grateful Dead\u2019s 60 Years With Emotional Post: \u2018Great Honor\u2019",
    "link": "https://www.rollingstone.com/music/music-news/john-mayer-grateful-dead-60-years-celebrates-1235401482/",
    "source": "Music News",
    "published": "Wed, 06 Aug 2025 00:29:14 +0000",
    "image": "https://www.rollingstone.com/wp-content/uploads/2025/08/GettyImages-2196432496-1.jpg?w=1600&h=900&crop=1"
  },
  {
    "title": "Acopia \u2013 \u201cReal Life\u201d",
    "link": "https://www.stereogum.com/2318309/acopia-real-life/music/",
    "source": "Stereogum",
    "published": "Tue, 05 Aug 2025 23:39:29 +0000",
    "image": null
  },
  {
    "title": "Westside Cowboy \u2013 \u201cDrunk Surfer\u201d",
    "link": "https://www.stereogum.com/2318304/westside-cowboy-drunk-surfer/music/",
    "source": "Stereogum",
    "published": "Tue, 05 Aug 2025 23:22:35 +0000",
    "image": null
  },
  {
    "title": "Sony Music Sues Napster Again 26 Years Later",
    "link": "https://www.stereogum.com/2318298/sony-music-sues-napster-again-26-years-later/news/",
    "source": "Stereogum",
    "published": "Tue, 05 Aug 2025 22:44:54 +0000",
    "image": null
  },
  {
    "title": "Freddie Gibbs and the Alchemist Announce North American Tour",
    "link": "https://pitchfork.com/news/freddie-gibbs-and-the-alchemist-announce-north-american-tour",
    "source": "RSS: News",
    "published": "Tue, 05 Aug 2025 22:30:06 +0000",
    "image": "https://media.pitchfork.com/photos/689255c36d72f898ceba52a3/master/pass/Freddie-Gibbs-The-Alchemist.jpg"
  },
  {
    "title": "25 New Songs Out Today",
    "link": "https://www.brooklynvegan.com/25-new-songs-out-today-59/",
    "source": "BrooklynVegan",
    "published": "Tue, 05 Aug 2025 22:02:54 +0000",
    "image": "https://media.brooklynvegan.com/xxrzsfjkyw/uploads/2025/08/05/WHITNEY-JOHNSON-LIA-KOHL-MACIE-STEWARTphoto-by-Leah-Wendzinski-1.jpg"
  },
  {
    "title": "Tour news: The Jesus Lizard, Yaya Bey, Dying Wish, Cavalera play Sepultura, Fred Armisen, The Hacienda, more",
    "link": "https://www.brooklynvegan.com/tour-news-the-jesus-lizard-yaya-bey-dying-wish-cavalera-play-sepultura-fred-armisen-the-hacienda-more/",
    "source": "BrooklynVegan",
    "published": "Tue, 05 Aug 2025 21:56:02 +0000",
    "image": "https://media.brooklynvegan.com/xxrzsfjkyw/uploads/2025/08/05/Yaya-Bey-photo-by-Cody-Lidtke.jpg"
  },
  {
    "title": "Mel Gibson\u2019s Passion of the Christ Sequel Split into Two Movies for 2027 Release",
    "link": "https://consequence.net/2025/08/resurrection-of-the-christ-release-dates/",
    "source": "Consequence",
    "published": "Tue, 05 Aug 2025 21:33:00 +0000",
    "image": "https://consequence.net/wp-content/uploads/2025/01/passion-of-the-christ-sequel-de-aging.jpg?quality=80"
  },
  {
    "title": "Samia Drops Stripped Version of \u2018Pool\u2019 After 2023 Tiny Desk Performance Goes Viral",
    "link": "https://www.rollingstone.com/music/music-news/samia-stripped-version-pool-2023-tiny-desk-viral-1235400957/",
    "source": "Music News",
    "published": "Tue, 05 Aug 2025 21:11:47 +0000",
    "image": "https://www.rollingstone.com/wp-content/uploads/2025/08/Samia-Pool.jpg?crop=0px%2C84px%2C1800px%2C1015px&resize=1600%2C900"
  },
  {
    "title": "Green Day get their own Garbage Pail Kids cards",
    "link": "https://www.brooklynvegan.com/green-day-get-their-own-garbage-pail-kids-cards/",
    "source": "BrooklynVegan",
    "published": "Tue, 05 Aug 2025 21:00:04 +0000",
    "image": "https://media.brooklynvegan.com/xxrzsfjkyw/uploads/2025/08/05/greenday-garbagepailkids.jpg"
  },
  {
    "title": "Justin Bieber Clears His Mind With a Family Vacation in \u2018Yukon\u2019 Video",
    "link": "https://www.rollingstone.com/music/music-news/justin-bieber-yukon-video-1235401055/",
    "source": "Music News",
    "published": "Tue, 05 Aug 2025 20:32:35 +0000",
    "image": "https://www.rollingstone.com/wp-content/uploads/2025/08/justin-bieber-yukon-vid.jpg?crop=0px%2C102px%2C1800px%2C1014px&resize=1600%2C900"
  },
  {
    "title": "Spotify Introduces Controversial Face-Scanning Age Check for UK Users",
    "link": "https://consequence.net/2025/08/spotify-face-scan-age-check-uk-users/",
    "source": "Consequence",
    "published": "Tue, 05 Aug 2025 20:18:27 +0000",
    "image": "https://consequence.net/wp-content/uploads/2025/08/Untitled_3b3584.jpeg?quality=80"
  },
  {
    "title": "Fcukers add NYC & LA shows to tour",
    "link": "https://www.brooklynvegan.com/fcukers-add-nyc-la-shows-to-tour/",
    "source": "BrooklynVegan",
    "published": "Tue, 05 Aug 2025 20:11:35 +0000",
    "image": "https://media.brooklynvegan.com/xxrzsfjkyw/uploads/2025/08/01/lollapalooza-2025-thu-078.jpg"
  },
  {
    "title": "The Lemonheads \u2013 \u201cThe Key Of Victory\u201d",
    "link": "https://www.stereogum.com/2318244/the-lemonheads-the-key-of-victory/music/",
    "source": "Stereogum",
    "published": "Tue, 05 Aug 2025 20:10:11 +0000",
    "image": null
  },
  {
    "title": "Soulja Boy Released from Custody as Gun Charge Rejected by Prosecutors",
    "link": "https://www.rollingstone.com/music/music-news/soulja-boy-arrest-gun-possession-prosecutor-declines-case-1235400868/",
    "source": "Music News",
    "published": "Tue, 05 Aug 2025 20:06:56 +0000",
    "image": "https://www.rollingstone.com/wp-content/uploads/2025/08/Soulja-Boy-da-rejects.jpg?crop=144px%2C26px%2C1656px%2C932px&resize=1600%2C900"
  },
  {
    "title": "Scharpling & Wurster celebrating The Best Show\u2019s 25th anniversary in Brooklyn, Philly, LA & Chicago",
    "link": "https://www.brooklynvegan.com/scharpling-wurster-celebrating-the-best-shows-25th-anniversary-in-brooklyn-philly-la-chicago/",
    "source": "BrooklynVegan",
    "published": "Tue, 05 Aug 2025 20:00:55 +0000",
    "image": "https://media.brooklynvegan.com/xxrzsfjkyw/uploads/2025/08/05/best-show-25th-anniversary-photo.jpeg"
  },
  {
    "title": "Staff Picks: Favorite Albums of July 2025",
    "link": "https://consequence.net/2025/08/best-albums-june-2025-staff-picks-2/",
    "source": "Consequence",
    "published": "Tue, 05 Aug 2025 19:45:03 +0000",
    "image": "https://consequence.net/wp-content/uploads/2025/08/Staff-Best-Albums-July25-1200x675-1.jpg?quality=80"
  },
  {
    "title": "Saint Etienne \u2013 \u201cTake Me To The Pilot\u201d",
    "link": "https://www.stereogum.com/2318268/saint-etienne-take-me-to-the-pilot/music/",
    "source": "Stereogum",
    "published": "Tue, 05 Aug 2025 19:22:33 +0000",
    "image": null
  },
  {
    "title": "Lizzo Is Recalibrating Her Relationship With Body Positivity After Weight Loss",
    "link": "https://www.rollingstone.com/music/music-news/lizzo-weight-loss-journey-depression-1235400733/",
    "source": "Music News",
    "published": "Tue, 05 Aug 2025 18:50:09 +0000",
    "image": "https://www.rollingstone.com/wp-content/uploads/2025/08/Lizzo-Weight-Loss-Journey.jpg?crop=0px%2C19px%2C1800px%2C1015px&resize=1600%2C900"
  },
  {
    "title": "Weakened Friends \u2013 \u201cNPC\u201d (Feat. Buckethead)",
    "link": "https://www.stereogum.com/2318262/weakened-friends-npc-feat-buckethead/music/",
    "source": "Stereogum",
    "published": "Tue, 05 Aug 2025 18:49:55 +0000",
    "image": null
  },
  {
    "title": "Big Thief Unveil New Songs \u201cLos Angeles\u201d and \u201cGrandmother\u201d: Stream",
    "link": "https://consequence.net/2025/08/big-thief-new-songs-los-angeles-grandmother/",
    "source": "Consequence",
    "published": "Tue, 05 Aug 2025 18:13:16 +0000",
    "image": "https://consequence.net/wp-content/uploads/2025/08/Hi-Res-Image-Big-Thief-by-Daniel-Arnold.jpg?quality=80"
  },
  {
    "title": "Win David Bowie\u2019s I Can\u2019t Give Everything Away (2002-2016) 18xLP Vinyl Box Set",
    "link": "https://www.stereogum.com/2318103/david-bowie-vinyl-box-set-2002-2016/giveaway/",
    "source": "Stereogum",
    "published": "Tue, 05 Aug 2025 18:12:00 +0000",
    "image": null
  },
  {
    "title": "Gorilla Biscuits & Orange 9MM announce CBGB Fest pre-show + other dates",
    "link": "https://www.brooklynvegan.com/gorilla-biscuits-orange-9mm-announce-cbgb-fest-pre-show-other-dates/",
    "source": "BrooklynVegan",
    "published": "Tue, 05 Aug 2025 17:59:13 +0000",
    "image": "https://media.brooklynvegan.com/xxrzsfjkyw/uploads/2025/08/05/gorillabiscuits-racket-crop.jpg"
  },
  {
    "title": "Jens Lekman \u2013 \u201cWedding In Liepzig\u201d",
    "link": "https://www.stereogum.com/2318187/jens-lekman-wedding-in-liepzig/music/",
    "source": "Stereogum",
    "published": "Tue, 05 Aug 2025 17:43:24 +0000",
    "image": null
  },
  {
    "title": "Terry Reid, Storied British Rocker, Dies at 75",
    "link": "https://pitchfork.com/news/terry-reid-storied-british-rocker-dies-at-75",
    "source": "RSS: News",
    "published": "Tue, 05 Aug 2025 17:37:32 +0000",
    "image": "https://media.pitchfork.com/photos/6892338e11737b28c9703620/master/pass/terry%20reid.jpg"
  },
  {
    "title": "Listen to Big Thief\u2019s New Songs \u201cLos Angeles\u201d and \u201cGrandmother\u201d",
    "link": "https://pitchfork.com/news/listen-to-big-thief-new-songs-los-angeles-and-grandmother",
    "source": "RSS: News",
    "published": "Tue, 05 Aug 2025 17:33:01 +0000",
    "image": "https://media.pitchfork.com/photos/68918c289ca3e7cde1f9bc1b/master/pass/%5BHi-Res%20Image%5D%20Big%20Thief%20by%20Daniel%20Arnold.jpg"
  },
  {
    "title": "Big Thief \u2013 \u201cLos Angeles\u201d & \u201cGrandmother\u201d (Feat. Laraaji)",
    "link": "https://www.stereogum.com/2318213/big-thief-los-angeles-grandmother-feat-laraaji/music/",
    "source": "Stereogum",
    "published": "Tue, 05 Aug 2025 17:31:48 +0000",
    "image": null
  },
  {
    "title": "David Byrne & Hayley Williams keep doing things, including a new collab for Netflix\u2019s \u2018The Twits\u2019",
    "link": "https://www.brooklynvegan.com/david-byrne-hayley-williams-keep-doing-things-including-a-new-collab-for-netflixs-the-twits/",
    "source": "BrooklynVegan",
    "published": "Tue, 05 Aug 2025 17:29:08 +0000",
    "image": "https://media.brooklynvegan.com/xxrzsfjkyw/uploads/2025/08/05/david-byrne-hayley-williams.jpeg"
  },
  {
    "title": "La Dispute Share Three More Songs From No One Was Driving The Car",
    "link": "https://www.stereogum.com/2318235/la-dispute-share-three-more-songs-from-no-one-was-driving-the-car/music/",
    "source": "Stereogum",
    "published": "Tue, 05 Aug 2025 17:19:25 +0000",
    "image": null
  },
  {
    "title": "Ozzy Osbourne Died Of A Heart Attack, Death Certificate Reveals",
    "link": "https://www.stereogum.com/2318231/ozzy-osbourne-died-of-a-heart-attack-death-certificate-reveals/news/",
    "source": "Stereogum",
    "published": "Tue, 05 Aug 2025 17:13:13 +0000",
    "image": null
  },
  {
    "title": "Samia Rushes Out Stripped-Down \u201cPool\u201d After Viral Tiny Desk Performance",
    "link": "https://www.stereogum.com/2318199/samia-rushes-out-stripped-down-pool-after-viral-tiny-desk-performance/music/",
    "source": "Stereogum",
    "published": "Tue, 05 Aug 2025 17:03:44 +0000",
    "image": null
  },
  {
    "title": "Terry Reid, Artists\u2019 Artist Who Nearly Became Led Zeppelin\u2019s Singer, Dead at 75",
    "link": "https://www.rollingstone.com/music/music-news/terry-reid-dead-led-zeppelin-obituary-1235400523/",
    "source": "Music News",
    "published": "Tue, 05 Aug 2025 17:01:24 +0000",
    "image": "https://www.rollingstone.com/wp-content/uploads/2025/08/GettyImages-180004939.jpg?w=1600&h=900&crop=1"
  },
  {
    "title": "The Dare Reveals His Love for Kacey Musgraves and Offers Some \u2018Editing\u2019 Advice to Justin Bieber",
    "link": "https://www.rollingstone.com/music/music-news/the-dare-talks-kacey-musgraves-justin-bieber-song-shuffle-1235400173/",
    "source": "Music News",
    "published": "Tue, 05 Aug 2025 17:00:18 +0000",
    "image": "https://www.rollingstone.com/wp-content/uploads/2025/08/the-dare-song-shuffle.jpg?w=1600&h=900&crop=1"
  },
  {
    "title": "Daron Malakian: System of a Down\u2019s Potential Replacement for Serj Tankian \u201cSounded Good,\u201d But It Felt Wrong",
    "link": "https://consequence.net/2025/08/daron-malakian-system-of-a-down-replacement-serj-tankian/",
    "source": "Consequence",
    "published": "Tue, 05 Aug 2025 16:59:33 +0000",
    "image": "https://consequence.net/wp-content/uploads/2025/08/Daron-Malakian-Serj-Tankian.jpg?quality=80"
  },
  {
    "title": "Ela Minus Announces Tour Dates, Shares Nick Le\u00f3n Remixes of \u201cQQQQ\u201d: Listen",
    "link": "https://pitchfork.com/news/ela-minus-announces-tour-dates-shares-nick-leon-remixes-of-qqqq-listen",
    "source": "RSS: News",
    "published": "Tue, 05 Aug 2025 16:54:36 +0000",
    "image": "https://media.pitchfork.com/photos/6891460e74b7b759d02e889a/master/pass/Ela-Minus.jpeg"
  },
  {
    "title": "Ozzy Osbourne\u2019s cause of death revealed",
    "link": "https://www.brooklynvegan.com/ozzy-osbournes-cause-of-death-revealed/",
    "source": "BrooklynVegan",
    "published": "Tue, 05 Aug 2025 16:53:02 +0000",
    "image": "https://media.brooklynvegan.com/xxrzsfjkyw/uploads/2025/07/22/Ozzy-2025.jpg"
  },
  {
    "title": "Terry Reid Dead At 75",
    "link": "https://www.stereogum.com/2318222/terry-reid-dead-at-75/news/",
    "source": "Stereogum",
    "published": "Tue, 05 Aug 2025 16:49:01 +0000",
    "image": null
  },
  {
    "title": "Mini Consequence Crossword: \u201cThe Addams Family\u201d",
    "link": "https://consequence.net/2025/08/mini-crossword-the-addams-family/",
    "source": "Consequence",
    "published": "Tue, 05 Aug 2025 16:43:45 +0000",
    "image": "https://consequence.net/wp-content/uploads/2025/08/crossword-the-addams-family.jpeg?quality=80"
  },
  {
    "title": "The Lemonheads Reveal New Song \u201cThe Key of Victory\u201d: Stream",
    "link": "https://consequence.net/2025/08/the-lemonheads-new-song-key-of-victory/",
    "source": "Consequence",
    "published": "Tue, 05 Aug 2025 16:40:56 +0000",
    "image": "https://consequence.net/wp-content/uploads/2025/08/The-Lemonheads-new-song-The-Key-of-Victory-by-Gareth-Jones-.jpg?quality=80"
  },
  {
    "title": "Have a Safe \u2018Trip\u2019",
    "link": "https://www.spin.com/2025/08/have-a-safe-trip/",
    "source": "SPIN",
    "published": "Tue, 05 Aug 2025 16:40:41 +0000",
    "image": "https://static.spin.com/files/2025/08/Copy-of-Shaman-scaled.jpg"
  },
  {
    "title": "Phantogram on How Intimate Shows, Touring with Deftones, and a Two-Piece Setup Are \u201cKeeping Us Stoked Creatively\u201d",
    "link": "https://consequence.net/2025/08/phantogram-interview-intimate-show-deftones/",
    "source": "Consequence",
    "published": "Tue, 05 Aug 2025 16:40:13 +0000",
    "image": "https://consequence.net/wp-content/uploads/2025/08/2025_06_26_KikiVassilakis_TheWHP_Phantogram_sm-302-of-378.jpg?quality=80"
  },
  {
    "title": "Ratboys, Squirrel Flower, The Ophelias, & More Cover Bad Bad Hats On Psychic Reader 10th Anniversary Edition",
    "link": "https://www.stereogum.com/2318141/ratboys-squirrel-flower-the-ophelias-more-cover-bad-bad-hats-on-psychic-reader-10th-anniversary-edition/music/",
    "source": "Stereogum",
    "published": "Tue, 05 Aug 2025 16:36:29 +0000",
    "image": null
  },
  {
    "title": "Matt Cameron Breaks Down the Drumming on Soundgarden\u2019s \u201cRusty Cage\u201d for Drumeo: Watch",
    "link": "https://consequence.net/2025/08/matt-cameron-drumeo-soundgarden-rusty-cage/",
    "source": "Consequence",
    "published": "Tue, 05 Aug 2025 16:33:14 +0000",
    "image": "https://consequence.net/wp-content/uploads/2025/08/matt-cameron-drumeo-soundgarden-rusty-cage.jpg?quality=80"
  },
  {
    "title": "Stream Japanese \u201cPost-Black Metal\u201d Band Asunojokei\u2019s Vibrant New Album Think Of You",
    "link": "https://www.stereogum.com/2318218/stream-japanese-post-black-metal-band-asunojokeis-vibrant-new-album-think-of-you/music/",
    "source": "Stereogum",
    "published": "Tue, 05 Aug 2025 16:19:19 +0000",
    "image": null
  },
  {
    "title": "MTV VMAs 2025 Nominees Announced: See the Full List Here",
    "link": "https://pitchfork.com/news/mtv-vmas-2025-nominees-announced-see-the-full-list-here",
    "source": "RSS: News",
    "published": "Tue, 05 Aug 2025 16:06:49 +0000",
    "image": "https://media.pitchfork.com/photos/68922ce311737b28c970361d/master/pass/VMAs.jpeg"
  },
  {
    "title": "Lady Gaga, Bruno Mars, Kendrick Lamar Lead MTV VMA Noms",
    "link": "https://www.spin.com/2025/08/mtv-vma-nominations/",
    "source": "SPIN",
    "published": "Tue, 05 Aug 2025 16:00:00 +0000",
    "image": "https://static.spin.com/files/2025/07/2225542855-scaled.jpg"
  },
  {
    "title": "Ozzy Osbourne\u2019s Cause Of Death Revealed",
    "link": "https://www.spin.com/2025/08/ozzy-osbourne-cause-of-death/",
    "source": "SPIN",
    "published": "Tue, 05 Aug 2025 15:59:00 +0000",
    "image": "https://static.spin.com/files/2023/03/GettyImages-73998640.jpg"
  },
  {
    "title": "Album Of The Week: Teethe Magic Of The Sale",
    "link": "https://www.stereogum.com/2318168/album-of-the-week-teethe-magic-of-the-sale/reviews/album-of-the-week/",
    "source": "Stereogum",
    "published": "Tue, 05 Aug 2025 15:58:24 +0000",
    "image": null
  },
  {
    "title": "David Byrne Contributes New Songs, Including A Hayley Williams Collab, To New Netflix Roald Dahl Adaptation The Twits",
    "link": "https://www.stereogum.com/2318208/david-byrne-contributes-new-songs-including-a-hayley-williams-collab-to-new-netflix-roald-dahl-adaptation-the-twits/news/",
    "source": "Stereogum",
    "published": "Tue, 05 Aug 2025 15:55:13 +0000",
    "image": null
  },
  {
    "title": "Aren\u2019t We Amphibians announce debut album \u2018Parade! Parade!,\u2019 share \u201cDunce Hat\u201d",
    "link": "https://www.brooklynvegan.com/arent-we-amphibians-announce-debut-album-parade-parade-share-dunce-hat/",
    "source": "BrooklynVegan",
    "published": "Tue, 05 Aug 2025 15:49:59 +0000",
    "image": "https://media.brooklynvegan.com/xxrzsfjkyw/uploads/2025/08/05/Arent-We-Amphibians.png"
  },
  {
    "title": "Ozzy Osbourne Died of a Heart Attack, Death Certificate Reveals",
    "link": "https://consequence.net/2025/08/ozzy-osbourne-cause-of-death/",
    "source": "Consequence",
    "published": "Tue, 05 Aug 2025 15:37:24 +0000",
    "image": "https://consequence.net/wp-content/uploads/2025/02/Ozzy-Osbourne.jpg?quality=80"
  },
  {
    "title": "Ozzy Osbourne\u2019s Cause of Death Revealed to Be a Heart Attack",
    "link": "https://pitchfork.com/news/ozzy-osbourne-cause-of-death-revealed-to-be-a-heart-attack",
    "source": "RSS: News",
    "published": "Tue, 05 Aug 2025 15:31:25 +0000",
    "image": "https://media.pitchfork.com/photos/689220d374b7b759d02e88de/master/pass/Ozzy-Osbourne.jpeg"
  },
  {
    "title": "The Pogues\u2019 Seminal Album Rum Sodomy & the Lash Receives 40th Anniversary Expanded Reissue",
    "link": "https://consequence.net/2025/08/the-pogues-rum-sodomy-the-lash-40th-anniversary-expanded-edition/",
    "source": "Consequence",
    "published": "Tue, 05 Aug 2025 15:27:30 +0000",
    "image": "https://consequence.net/wp-content/uploads/2025/08/pogues-rum-sodom-2-cd.jpg?quality=80"
  },
  {
    "title": "Saintseneca \u2013 \u201cSweet Nothing\u201d",
    "link": "https://www.stereogum.com/2318205/saintseneca-sweet-nothing/music/",
    "source": "Stereogum",
    "published": "Tue, 05 Aug 2025 15:21:59 +0000",
    "image": null
  },
  {
    "title": "Riot Fest announces 2025 aftershows (Sex Pistols, The Damned, Texas is the Reason, Alkaline Trio, more)",
    "link": "https://www.brooklynvegan.com/riot-fest-announces-2025-aftershows-sex-pistols-the-damned-texas-is-the-reason-alkaline-trio-more/",
    "source": "BrooklynVegan",
    "published": "Tue, 05 Aug 2025 15:20:30 +0000",
    "image": "https://media.brooklynvegan.com/xxrzsfjkyw/uploads/2025/08/05/riotfest-2025-aftershows-crop.jpg"
  },
  {
    "title": "Stella Donnelly \u2013 \u201cBaths\u201d & \u201cStanding Ovation\u201d",
    "link": "https://www.stereogum.com/2318186/stella-donnelly-baths-standing-ovation/music/",
    "source": "Stereogum",
    "published": "Tue, 05 Aug 2025 15:13:39 +0000",
    "image": null
  },
  {
    "title": "AFI Announce New Album Silver Bleeds The Black Sun\u2026: Hear \u201cBehind The Clock\u201d",
    "link": "https://www.stereogum.com/2318194/afi-announce-new-album-silver-bleeds-the-black-sun-hear-behind-the-clock/music/",
    "source": "Stereogum",
    "published": "Tue, 05 Aug 2025 14:56:45 +0000",
    "image": null
  },
  {
    "title": "Freddie Gibbs & The Alchemist announce fall tour with MAVI & others",
    "link": "https://www.brooklynvegan.com/freddie-gibbs-the-alchemist-announce-fall-tour-with-mavi-others/",
    "source": "BrooklynVegan",
    "published": "Tue, 05 Aug 2025 14:42:11 +0000",
    "image": "https://media.brooklynvegan.com/xxrzsfjkyw/uploads/2025/07/17/freddiegibbs-thealchemist-NickWalker.jpg"
  },
  {
    "title": "Pip Blom & Personal Trainer\u2019s Willem Smit Announce Debut Album As Long Fling: Hear \u201cFlung\u201d",
    "link": "https://www.stereogum.com/2318180/pip-blom-personal-trainers-willem-smit-announce-debut-album-as-long-fling-hear-flung/music/",
    "source": "Stereogum",
    "published": "Tue, 05 Aug 2025 14:28:58 +0000",
    "image": null
  },
  {
    "title": "Hayley Williams Shares \u201cEgo Death At A Bachelorette Party\u201d Video, Discusses Country Musician Nashville Bars",
    "link": "https://www.stereogum.com/2318169/hayley-williams-shares-ego-death-at-a-bachelorette-party-video-discusses-country-musician-nashville-bars/news/",
    "source": "Stereogum",
    "published": "Tue, 05 Aug 2025 14:19:38 +0000",
    "image": null
  },
  {
    "title": "The Jesus Lizard Cancel 2025 Tour Due to \u201cSerious Health Incident\u201d",
    "link": "https://pitchfork.com/news/the-jesus-lizard-cancel-2025-tour-due-to-serious-health-incident",
    "source": "RSS: News",
    "published": "Tue, 05 Aug 2025 14:18:02 +0000",
    "image": "https://media.pitchfork.com/photos/6892121dd8fbcf2882b46741/master/pass/GettyImages-2182416962.jpg"
  },
  {
    "title": "Ela Minus shares remix EP, announces fall tour",
    "link": "https://www.brooklynvegan.com/ela-minus-shares-remix-ep-announces-fall-tour/",
    "source": "BrooklynVegan",
    "published": "Tue, 05 Aug 2025 14:17:54 +0000",
    "image": "https://media.brooklynvegan.com/xxrzsfjkyw/uploads/2025/08/05/ela-minus.jpg"
  },
  {
    "title": "Watch Hayley Williams\u2019 New Video for \u201cEgo Death at a Bachelorette Party\u201d",
    "link": "https://pitchfork.com/news/watch-hayley-williams-new-video-for-ego-death-at-a-bachelorette-party",
    "source": "RSS: News",
    "published": "Tue, 05 Aug 2025 14:17:53 +0000",
    "image": "https://media.pitchfork.com/photos/68918899aed5e2fe36282e7b/master/pass/Screenshot%202025-08-04%20at%2011.29.01%E2%80%AFPM.png"
  },
  {
    "title": "How Two Music Startups Turned Templates Into Educational Tools",
    "link": "https://www.spin.com/2025/08/how-two-music-startups-turned-templates-into-educational-tools/",
    "source": "SPIN",
    "published": "Tue, 05 Aug 2025 14:07:15 +0000",
    "image": "https://static.spin.com/files/2025/08/1200x600px-Ableton-v2.png"
  },
  {
    "title": "AFI go goth on new album \u2018Silver Bleeds the Black Sun\u2019 (hear a track)",
    "link": "https://www.brooklynvegan.com/afi-go-goth-on-new-album-silver-bleeds-the-black-sun-hear-a-track/",
    "source": "BrooklynVegan",
    "published": "Tue, 05 Aug 2025 14:01:00 +0000",
    "image": "https://media.brooklynvegan.com/xxrzsfjkyw/uploads/2025/08/04/AFI-by-Lexie-Alley.jpg"
  },
  {
    "title": "Hayley Williams Has A Nashville \u2018Party\u2019 In New Video",
    "link": "https://www.spin.com/2025/08/hayley-williams-ego-death-video/",
    "source": "SPIN",
    "published": "Tue, 05 Aug 2025 14:00:00 +0000",
    "image": "https://static.spin.com/files/2025/08/NFF-2025-Bleachers-Ally-Coalition-Photo-Kissick-13-scaled.jpg"
  },
  {
    "title": "Retirement Party Announce New Nothing To Hear Without A Sound EP: Hear \u201cSixth Sense\u201d",
    "link": "https://www.stereogum.com/2318145/retirement-party-announce-new-nothing-to-hear-without-a-sound-ep-hear-sixth-sense/music/",
    "source": "Stereogum",
    "published": "Tue, 05 Aug 2025 13:48:27 +0000",
    "image": null
  },
  {
    "title": "Orcutt Shelley Miller \u2013 \u201cFour-door Charger\u201d",
    "link": "https://www.stereogum.com/2318172/orcutt-shelley-miller-four-door-charger/music/",
    "source": "Stereogum",
    "published": "Tue, 05 Aug 2025 13:42:56 +0000",
    "image": null
  },
  {
    "title": "Joan Shelley announces new album & tour, shares \u201cEverybody\u201d",
    "link": "https://www.brooklynvegan.com/joan-shelley-announces-new-album-tour-shares-everybody/",
    "source": "BrooklynVegan",
    "published": "Tue, 05 Aug 2025 13:29:40 +0000",
    "image": "https://media.brooklynvegan.com/xxrzsfjkyw/uploads/2025/08/05/Joan-Shelley_Nick-Rasmussen_2.jpg"
  },
  {
    "title": "Algernon Cadwallader Announce First New Album In 14 Years Trying Not To Have A Thought",
    "link": "https://www.stereogum.com/2318132/algernon-cadwallader-announce-first-new-album-in-14-years-trying-not-to-have-a-thought/music/",
    "source": "Stereogum",
    "published": "Tue, 05 Aug 2025 13:11:01 +0000",
    "image": null
  },
  {
    "title": "The Jesus Lizard Cancel International Tour Due To \u201cSerious Health Incident\u201d",
    "link": "https://www.stereogum.com/2318164/the-jesus-lizard-cancel-international-tour-due-to-serious-health-incident/news/",
    "source": "Stereogum",
    "published": "Tue, 05 Aug 2025 13:06:57 +0000",
    "image": null
  },
  {
    "title": "Algernon Cadwallader announce first album in 14 years & tour, share \u201cHawk\u201d",
    "link": "https://www.brooklynvegan.com/algernon-cadwallader-announce-first-album-in-14-years-tour-share-hawk/",
    "source": "BrooklynVegan",
    "published": "Tue, 05 Aug 2025 13:00:14 +0000",
    "image": "https://media.brooklynvegan.com/xxrzsfjkyw/uploads/2025/08/04/Algernon-Cadwallader-by-Scott-Troyan-1.jpeg"
  },
  {
    "title": "Algernon Cadwallader Announce Tour and First Album in 14 Years, Share Video for New Song: Watch",
    "link": "https://pitchfork.com/news/algernon-cadwallader-announce-tour-and-first-album-in-14-years-share-video-for-new-song-watch",
    "source": "RSS: News",
    "published": "Tue, 05 Aug 2025 13:00:04 +0000",
    "image": "https://media.pitchfork.com/photos/6890d7b239f5b3ea9fca3f00/master/pass/Algernon-Cadwallader-1.jpeg"
  },
  {
    "title": "GHOSTBUSTER",
    "link": "https://www.spin.com/2025/08/sunny-war/",
    "source": "SPIN",
    "published": "Tue, 05 Aug 2025 11:30:00 +0000",
    "image": "https://static.spin.com/files/2025/08/SunnyWar4-resized.jpg"
  }
]