[
  {
    "title": "Taylor Swift Deposition Off Limits to Justin Baldoni, Judge Rules: Lack of \u2018Appropriate Diligence\u2019",
    "link": "https://www.rollingstone.com/music/music-news/taylor-swift-deposition-denied-justin-baldoni-1235426835/",
    "source": "Music News",
    "published": "Sat, 13 Sep 2025 01:47:58 +0000",
    "image": "https://www.rollingstone.com/wp-content/uploads/2025/09/GettyImages-2197310482.jpg?w=1600&h=900&crop=1"
  },
  {
    "title": "Sharon Osbourne Thanks Fans for \u2018Overwhelming Love\u2019 After Ozzy\u2019s Death",
    "link": "https://www.rollingstone.com/music/music-news/sharon-osbourne-ozzy-osbourne-death-thanks-fans-1235426832/",
    "source": "Music News",
    "published": "Sat, 13 Sep 2025 00:50:14 +0000",
    "image": "https://www.rollingstone.com/wp-content/uploads/2025/09/Sharon-Osbourne-ozzy.jpg?w=1600&h=900&crop=1"
  },
  {
    "title": "Song of the Week: Spinal Tap Enlist Paul McCartney for the Downright Joyous \u201cCups and Cakes\u201d",
    "link": "https://consequence.net/2025/09/spinal-tap-cups-and-cakes-paul-mccartney/",
    "source": "Consequence",
    "published": "Sat, 13 Sep 2025 00:34:09 +0000",
    "image": "https://consequence.net/wp-content/uploads/2025/09/Spinal-Tap-Cups-and-Cakes-Song-of-the-Week.jpg?quality=80"
  },
  {
    "title": "Sphere Stock Continues to Soar, Gaining 46% in Last 4 Weeks on \u2018Wizard of Oz\u2019\u00a0Success",
    "link": "https://www.billboard.com/pro/sphere-stock-wizard-of-oz-gains-up/",
    "source": "Billboard",
    "published": "Sat, 13 Sep 2025 00:08:57 +0000",
    "image": "https://www.billboard.com/wp-content/uploads/2025/09/sphere-wizard-of-oz-red-slippers-billboard-1800.jpg?w=1024"
  },
  {
    "title": "In Canada: The Beaches Named Billboard Canada\u2019s Women of the Year\u00a02025",
    "link": "https://www.billboard.com/pro/the-beaches-billboard-canada-women-of-the-year/",
    "source": "Billboard",
    "published": "Fri, 12 Sep 2025 23:53:50 +0000",
    "image": "https://www.billboard.com/wp-content/uploads/2025/09/the-beaches-grammy-museum-2025-billboard-1800.jpg?w=1024"
  },
  {
    "title": "Hunting for the Next HUNTR/X: Galaxy Corporation Holds L.A. Auditions for Virtual K-Pop\u00a0Group",
    "link": "https://www.billboard.com/business/tech/virtual-kpop-group-galaxy-corporation-la-auditions-1236064288/",
    "source": "Billboard",
    "published": "Fri, 12 Sep 2025 23:32:00 +0000",
    "image": "https://www.billboard.com/wp-content/uploads/2025/09/el-rey-galaxy-corporation-auditions-2025-billboard-1800.jpg?w=1024"
  },
  {
    "title": "Kansas City Chiefs vs. Philadelphia Eagles: How to Watch 2025 Super Bowl Rematch\u00a0Online",
    "link": "https://www.billboard.com/culture/product-recommendations/kansas-city-chiefs-philadelphia-eagles-watch-online-1236065916/",
    "source": "Billboard",
    "published": "Fri, 12 Sep 2025 23:04:50 +0000",
    "image": "https://www.billboard.com/wp-content/uploads/2025/09/patrick-mahomes-super-bowl-2025-billboard-1800.jpg?w=1024"
  },
  {
    "title": "Akon\u2019s Wife Files for Divorce After 29 Years of\u00a0Marriage",
    "link": "https://www.billboard.com/music/rb-hip-hop/akon-divorce-tameka-thiam-files-29-years-marriage-1236065967/",
    "source": "Billboard",
    "published": "Fri, 12 Sep 2025 23:01:02 +0000",
    "image": "https://www.billboard.com/wp-content/uploads/2025/09/Tomeka-Thiam-Akon-BET-awards-2024-billboard-1800.jpg?w=1024"
  },
  {
    "title": "Tate McRae Welcomes Megan Moroney for Duet of \u20186 Months Later\u2019 at Nashville Show",
    "link": "https://www.rollingstone.com/music/music-news/tate-mcrae-megan-moroney-duet-6-months-later-nashville-show-1235426794/",
    "source": "Music News",
    "published": "Fri, 12 Sep 2025 22:47:06 +0000",
    "image": "https://www.rollingstone.com/wp-content/uploads/2025/09/megan-tate.jpg?w=1600&h=900&crop=1"
  },
  {
    "title": "Mexican Cuisine, Orchestral Sounds & \u2018Mutual Appreciation\u2019 of New Generation: How David Byrne Created His \u2018Who Is the Sky?\u2019\u00a0Album",
    "link": "https://www.billboard.com/music/rock/david-byrne-new-album-who-is-the-sky-interview-1236065932/",
    "source": "Billboard",
    "published": "Fri, 12 Sep 2025 22:19:11 +0000",
    "image": "https://www.billboard.com/wp-content/uploads/2025/09/david-byrne-2025-credit-Shervin-Lainez-billboard-1800.jpg?w=1024"
  },
  {
    "title": "Our Favorite Songs of the Week (Playlist)",
    "link": "https://www.brooklynvegan.com/our-favorite-songs-of-the-week-playlist-214/",
    "source": "BrooklynVegan",
    "published": "Fri, 12 Sep 2025 21:50:29 +0000",
    "image": null
  },
  {
    "title": "21 New Songs Out Today",
    "link": "https://www.brooklynvegan.com/21-new-songs-out-today-85/",
    "source": "BrooklynVegan",
    "published": "Fri, 12 Sep 2025 21:34:22 +0000",
    "image": null
  },
  {
    "title": "Daniel Day-Lewis \u201cNever Intended\u201d Retirement from Acting: \u201cI Just Wanted to Work on Something Else for a While\u201d",
    "link": "https://consequence.net/2025/09/daniel-day-lewis-retirement-comments/",
    "source": "Consequence",
    "published": "Fri, 12 Sep 2025 21:21:37 +0000",
    "image": "https://consequence.net/wp-content/uploads/2025/09/daniel-day-lewis-denies-retiring.jpg?quality=80"
  },
  {
    "title": "Tour news: Lady Gaga, Madison Cunningham, Stereolab, LCD Soundsystem, Skullcrusher, Prince Paul, more",
    "link": "https://www.brooklynvegan.com/tour-news-lady-gaga-madison-cunningham-stereolab-lcd-soundsystem-skullcrusher-prince-paul-more/",
    "source": "BrooklynVegan",
    "published": "Fri, 12 Sep 2025 21:17:18 +0000",
    "image": null
  },
  {
    "title": "M\u00f6tley Cr\u00fce\u2019s Vince Neil Suffered Stroke Last December: \u2018I Had to Learn to Walk Again\u2019",
    "link": "https://www.rollingstone.com/music/music-news/motley-crue-vince-neil-stroke-1235426749/",
    "source": "Music News",
    "published": "Fri, 12 Sep 2025 21:10:56 +0000",
    "image": "https://www.rollingstone.com/wp-content/uploads/2025/09/motley-crue-vince-neil.jpg?w=1600&h=900&crop=1"
  },
  {
    "title": "Djo Just Dropped His Second Album Of 2025",
    "link": "https://www.stereogum.com/2322853/djo-just-dropped-his-second-album-of-2025/music/",
    "source": "Stereogum",
    "published": "Fri, 12 Sep 2025 21:04:20 +0000",
    "image": null
  },
  {
    "title": "Saintseneca announce fall tour with Radiator Hospital",
    "link": "https://www.brooklynvegan.com/saintseneca-announce-fall-tour-with-radiator-hospital/",
    "source": "BrooklynVegan",
    "published": "Fri, 12 Sep 2025 20:54:59 +0000",
    "image": null
  },
  {
    "title": "John Fogerty Bringing CCR Classics to Las Vegas Residency",
    "link": "https://consequence.net/2025/09/john-fogerty-ccr-las-vegas-residency/",
    "source": "Consequence",
    "published": "Fri, 12 Sep 2025 20:54:20 +0000",
    "image": "https://consequence.net/wp-content/uploads/2025/09/john-fogerty-las-vegas-residency-2026.jpg?quality=80"
  },
  {
    "title": "Every song on the \u2018Spinal Tap 2: The End Continues\u2019 soundtrack",
    "link": "https://www.nme.com/news/film/spinal-tap-2-the-end-continues-soundtrack-3892081?utm_source=rss&utm_medium=rss&utm_campaign=spinal-tap-2-the-end-continues-soundtrack",
    "source": "News | NME",
    "published": "Fri, 12 Sep 2025 20:34:33 +0000",
    "image": "https://www.nme.com/wp-content/uploads/2025/09/Spinal_Tap_2_Stonehenge.jpg"
  },
  {
    "title": "Sink Your Teeth Into Cafun\u00e9\u2019s New Album Bite Reality",
    "link": "https://www.stereogum.com/2322845/sink-your-teeth-into-cafunes-new-album-bite-reality/music/",
    "source": "Stereogum",
    "published": "Fri, 12 Sep 2025 20:29:36 +0000",
    "image": null
  },
  {
    "title": "Every song on \u2018The Long Walk\u2019 soundtrack",
    "link": "https://www.nme.com/news/film/the-long-walk-soundtrack-every-song-3892073?utm_source=rss&utm_medium=rss&utm_campaign=the-long-walk-soundtrack-every-song",
    "source": "News | NME",
    "published": "Fri, 12 Sep 2025 20:28:19 +0000",
    "image": "https://www.nme.com/wp-content/uploads/2025/09/The-Long-Walk-main.jpg"
  },
  {
    "title": "Neil Young and the Chrome Hearts Sued by Luxury Brand Chrome Hearts",
    "link": "https://www.rollingstone.com/music/music-news/neil-young-chrome-hearts-trademark-infringement-lawsuit-1235426674/",
    "source": "Music News",
    "published": "Fri, 12 Sep 2025 20:26:36 +0000",
    "image": "https://www.rollingstone.com/wp-content/uploads/2025/09/GettyImages-2212180409.jpg?w=1600&h=900&crop=1"
  },
  {
    "title": "Yves Tumor Rips Swedish House Mafia Fans as \u201cCorniest People\u201d After Being Booed Offstage",
    "link": "https://consequence.net/2025/09/yves-tumor-swedish-house-mafia-fans/",
    "source": "Consequence",
    "published": "Fri, 12 Sep 2025 20:26:14 +0000",
    "image": "https://consequence.net/wp-content/uploads/2025/09/yves-tumor-swedish-hour-mafia.jpg?quality=80"
  },
  {
    "title": "\u2018The US Office\u2019 was \u201cjaw-droppingly\u201d offensive and would be \u201cvery, very different\u201d if made today, says Rainn Wilson",
    "link": "https://www.nme.com/news/tv/the-us-office-was-jaw-droppingly-offensive-and-would-be-very-very-different-if-made-today-says-rainn-wilson-3892366?utm_source=rss&utm_medium=rss&utm_campaign=the-us-office-was-jaw-droppingly-offensive-and-would-be-very-very-different-if-made-today-says-rainn-wilson",
    "source": "News | NME",
    "published": "Fri, 12 Sep 2025 20:16:26 +0000",
    "image": "https://www.nme.com/wp-content/uploads/2022/11/Dwight-the-office.jpg"
  },
  {
    "title": "M\u00f6tley Cr\u00fce\u2019s Vince Neil Reveals He Suffered a Stroke Last Christmas",
    "link": "https://consequence.net/2025/09/motley-crue-vince-neil-suffered-stroke/",
    "source": "Consequence",
    "published": "Fri, 12 Sep 2025 20:07:36 +0000",
    "image": "https://consequence.net/wp-content/uploads/2025/09/Vince-Neil.jpg?quality=80"
  },
  {
    "title": "Luh Tyler \u2013 \u201cYoung Player\u201d (Feat. Larry June)",
    "link": "https://www.stereogum.com/2322842/luh-tyler-young-player-feat-larry-june/music/",
    "source": "Stereogum",
    "published": "Fri, 12 Sep 2025 20:04:43 +0000",
    "image": null
  },
  {
    "title": "Supergrass celebrated \u2018I Should Coco\u2019 @ The Rooftop at Pier 17 (pics, setlist)",
    "link": "https://www.brooklynvegan.com/supergrass-celebrated-i-should-coco-the-rooftop-at-pier-17-pics-setlist/",
    "source": "BrooklynVegan",
    "published": "Fri, 12 Sep 2025 20:04:11 +0000",
    "image": null
  },
  {
    "title": "Watch Sarah McLachlan, Olivia Rodrigo Discuss Lilith Fair\u2019s Impact in New Doc Trailer",
    "link": "https://www.rollingstone.com/music/music-news/lilith-fair-documentary-trailer-1235426604/",
    "source": "Music News",
    "published": "Fri, 12 Sep 2025 19:43:50 +0000",
    "image": "https://www.rollingstone.com/wp-content/uploads/2025/09/StPaula-Cole-Lilith-Fair-pc-Merri-Cyr.jpg?w=1600&h=900&crop=1"
  },
  {
    "title": "dEUS to play classics \u2018Worst Case Scenario\u2019 and \u2018In A Bar, Under The Sea\u2019 in full on 30th anniversary 2026 UK and European tour",
    "link": "https://www.nme.com/news/music/deus-to-play-classics-worst-case-scenario-and-in-a-bar-under-the-sea-in-full-on-30th-anniversary-2026-uk-and-european-tour-3892362?utm_source=rss&utm_medium=rss&utm_campaign=deus-to-play-classics-worst-case-scenario-and-in-a-bar-under-the-sea-in-full-on-30th-anniversary-2026-uk-and-european-tour",
    "source": "News | NME",
    "published": "Fri, 12 Sep 2025 19:36:51 +0000",
    "image": "https://www.nme.com/wp-content/uploads/2025/09/deus-1996-paul-bergen-1.jpg"
  },
  {
    "title": "Watch Charly Bliss Debut New Song \u201cMadrid\u201d And Cover Yellowcard On NYC Concert Cruise",
    "link": "https://www.stereogum.com/2322837/watch-charly-bliss-debut-new-song-madrid-and-cover-yellowcard-on-nyc-concert-cruise/news/",
    "source": "Stereogum",
    "published": "Fri, 12 Sep 2025 19:30:42 +0000",
    "image": null
  },
  {
    "title": "Cash Cobain Lights Up Brooklyn at Weedmaps\u2019 Kickback Event: Recap + Photos",
    "link": "https://consequence.net/2025/09/cash-cobain-brooklyn-weedmaps-kickback/",
    "source": "Consequence",
    "published": "Fri, 12 Sep 2025 19:11:46 +0000",
    "image": "https://consequence.net/wp-content/uploads/2025/09/cash-cobain-weedmaps-seventh-letter-kickback-event-recap-review-hip-hop-show-brooklyn-concert-show-99-scott.jpg?quality=80"
  },
  {
    "title": "Radioactivity Announce New Album Time Won\u2019t Bring Me Down: Hear The Title Track",
    "link": "https://www.stereogum.com/2322833/radioactivity-announce-new-album-time-wont-bring-me-down-hear-the-title-track/music/",
    "source": "Stereogum",
    "published": "Fri, 12 Sep 2025 19:09:24 +0000",
    "image": null
  },
  {
    "title": "Frog \u2013 \u201cSAX-A-MA-PHONE VAR. XII\u201d",
    "link": "https://www.stereogum.com/2322824/frog-sax-a-ma-phone-var-xii/music/",
    "source": "Stereogum",
    "published": "Fri, 12 Sep 2025 19:03:09 +0000",
    "image": null
  },
  {
    "title": "The 5 Best Songs Of The Week",
    "link": "https://www.stereogum.com/2322699/the-5-best-songs-of-the-week-595/lists/the-5-best-songs-of-the-week/",
    "source": "Stereogum",
    "published": "Fri, 12 Sep 2025 19:00:32 +0000",
    "image": null
  },
  {
    "title": "The Who Announce Final Show of North American Farewell Tour",
    "link": "https://consequence.net/2025/09/the-who-final-show-north-american-farewell-tour/",
    "source": "Consequence",
    "published": "Fri, 12 Sep 2025 18:52:28 +0000",
    "image": "https://consequence.net/wp-content/uploads/2025/09/The-Who.jpg?quality=80"
  },
  {
    "title": "Stream JADE\u2019s Ambitious, Fired-Up Solo Debut That\u2019s Showbiz Baby!",
    "link": "https://www.stereogum.com/2322825/stream-jades-ambitious-fired-up-solo-debut-thats-showbiz-baby/music/",
    "source": "Stereogum",
    "published": "Fri, 12 Sep 2025 18:50:07 +0000",
    "image": null
  },
  {
    "title": "Limp Bizkit Know How to Get Your Attention With New Song \u2018Making Love to Morgan Wallen\u2019",
    "link": "https://www.rollingstone.com/music/music-news/limp-bizkit-new-song-making-love-to-morgan-wallen-1235426548/",
    "source": "Music News",
    "published": "Fri, 12 Sep 2025 18:45:33 +0000",
    "image": "https://www.rollingstone.com/wp-content/uploads/2025/09/GettyImages-2231700594.jpg?w=1600&h=900&crop=1"
  },
  {
    "title": "Taylor Swift Has Not Agreed to Deposition in Blake Lively, Justin Baldoni Case \u2014 But She May Be \u2018Forced\u2019",
    "link": "https://www.rollingstone.com/music/music-news/taylor-swift-blake-lively-lawsuit-justin-baldoni-deposition-1235426306/",
    "source": "Music News",
    "published": "Fri, 12 Sep 2025 18:41:14 +0000",
    "image": "https://www.rollingstone.com/wp-content/uploads/2025/09/blake-taylor-justin-deposition.jpg?crop=0px%2C0px%2C1800px%2C1014px&resize=1600%2C900"
  },
  {
    "title": "Djo shares new \u201ccompanion piece\u201d album to \u2018The Crux\u2019 with 12 new songs",
    "link": "https://www.nme.com/news/music/djo-shares-new-companion-piece-album-to-the-crux-with-12-new-songs-3892358?utm_source=rss&utm_medium=rss&utm_campaign=djo-shares-new-companion-piece-album-to-the-crux-with-12-new-songs",
    "source": "News | NME",
    "published": "Fri, 12 Sep 2025 18:38:31 +0000",
    "image": "https://www.nme.com/wp-content/uploads/2025/09/djo-piers-greenan-1.jpg"
  },
  {
    "title": "Little Simz \u2013 \u201cDon\u2019t Leave Too Soon\u201d",
    "link": "https://www.stereogum.com/2322820/little-simz-dont-leave-too-soon/music/",
    "source": "Stereogum",
    "published": "Fri, 12 Sep 2025 18:29:12 +0000",
    "image": null
  },
  {
    "title": "Alright! Pulp were perfection at Forest Hills Stadium: review, pics, full video",
    "link": "https://www.brooklynvegan.com/alright-pulp-were-perfection-at-forest-hills-stadium-review-pics-full-video/",
    "source": "BrooklynVegan",
    "published": "Fri, 12 Sep 2025 18:05:52 +0000",
    "image": null
  },
  {
    "title": "Jane Remover Shares \u201cDreamflasher\u201d Video and New Song Featuring Lucy Bedroque: Watch",
    "link": "https://pitchfork.com/news/jane-remover-shares-dreamflasher-video-and-new-song-featuring-lucy-bedroque-watch",
    "source": "RSS: News",
    "published": "Fri, 12 Sep 2025 17:53:28 +0000",
    "image": "https://media.pitchfork.com/photos/68c45254c6560bfcdb8878a3/master/pass/Jane-Remover.jpeg"
  },
  {
    "title": "Flea\u2019s Silverlake Conservatory Students Release Red Hot Chili Peppers Tribute EP: Stream",
    "link": "https://consequence.net/2025/09/flea-silverlake-conservatory-students-red-hot-chili-peppers-tribute-ep/",
    "source": "Consequence",
    "published": "Fri, 12 Sep 2025 17:17:38 +0000",
    "image": "https://consequence.net/wp-content/uploads/2025/09/SCM-Our-Loving-Tribute-to-RHCP.jpg?quality=80"
  },
  {
    "title": "Jeff Tweedy \u2013 \u201cLou Reed Was My Babysitter\u201d",
    "link": "https://www.stereogum.com/2322738/jeff-tweedy-lou-reed-was-my-babysitter/music/",
    "source": "Stereogum",
    "published": "Fri, 12 Sep 2025 17:11:22 +0000",
    "image": null
  },
  {
    "title": "Ed Sheeran Celebrates \u2018Play\u2019 With Live Tiny Desk Concert",
    "link": "https://www.rollingstone.com/music/music-news/ed-sheeran-performs-play-live-tiny-desk-1235426343/",
    "source": "Music News",
    "published": "Fri, 12 Sep 2025 17:01:26 +0000",
    "image": "https://www.rollingstone.com/wp-content/uploads/2025/09/ed-sheeran-tiny-desk.jpg?w=1600&h=900&crop=1"
  },
  {
    "title": "Stereolab Release New Songs \u201cFed Up With Your Job\u201d and \u201cConstant and Uniform Movement Unknown\u201d: Listen",
    "link": "https://pitchfork.com/news/stereolab-release-new-songs-fed-up-with-your-job-and-constant-and-uniform-movement-unknown-listen",
    "source": "RSS: News",
    "published": "Fri, 12 Sep 2025 17:00:07 +0000",
    "image": "https://media.pitchfork.com/photos/68c332a5f3d227bacdfcb79b/master/pass/Stereolab.jpeg"
  },
  {
    "title": "Jeff Tweedy Shares Video for New Song \u201cLou Reed Was My Babysitter\u201d: Watch",
    "link": "https://pitchfork.com/news/jeff-tweedy-shares-video-for-new-song-lou-reed-was-my-babysitter-watch",
    "source": "RSS: News",
    "published": "Fri, 12 Sep 2025 16:57:54 +0000",
    "image": "https://media.pitchfork.com/photos/68c33174a8850bbdc4411f87/master/pass/Wilco-Jeff-Tweedy.jpeg"
  },
  {
    "title": "Heavy Song of the Week: HEALTH Channel Anger and Fear on \u201cORDINARY LOSS\u201d",
    "link": "https://consequence.net/2025/09/heavy-song-of-the-week-health-ordinary-loss/",
    "source": "Consequence",
    "published": "Fri, 12 Sep 2025 16:26:47 +0000",
    "image": "https://consequence.net/wp-content/uploads/2025/09/health-ordinary-loss-hsotw.jpg?quality=80"
  },
  {
    "title": "Luxury Fashion Brand Chrome Hearts Sues Neil Young",
    "link": "https://www.stereogum.com/2322811/luxury-fashion-brand-chrome-hearts-sues-neil-young/news/",
    "source": "Stereogum",
    "published": "Fri, 12 Sep 2025 16:17:30 +0000",
    "image": null
  },
  {
    "title": "Neil Young Sued by Chrome Hearts Fashion Brand Over New Band\u2019s Name",
    "link": "https://pitchfork.com/news/neil-young-sued-by-chrome-hearts-fashion-brand-over-new-band-name",
    "source": "RSS: News",
    "published": "Fri, 12 Sep 2025 16:15:36 +0000",
    "image": "https://media.pitchfork.com/photos/68c43f94c6560bfcdb88789f/master/pass/Neil-Young.jpeg"
  },
  {
    "title": "LCD Soundsystem Announce 2025 NYC Residency",
    "link": "https://consequence.net/2025/09/lcd-soundsystem-2025-nyc-residency/",
    "source": "Consequence",
    "published": "Fri, 12 Sep 2025 15:55:15 +0000",
    "image": "https://consequence.net/wp-content/uploads/2025/09/lcd-soundsystem-2025-nyc-residency-poster.jpg?quality=80"
  },
  {
    "title": "Radioactivity announce first album in 10 years, \u2018Time Won\u2019t Bring Me Down,\u2019 share title track",
    "link": "https://www.brooklynvegan.com/radioactivity-announce-first-album-in-10-years-time-wont-bring-me-down-share-title-track/",
    "source": "BrooklynVegan",
    "published": "Fri, 12 Sep 2025 15:48:51 +0000",
    "image": null
  },
  {
    "title": "Taylor Swift Deposition Not Happening Despite Justin Baldoni\u2019s Lawyer Claim",
    "link": "https://www.stereogum.com/2322804/taylor-swift-confirmed-to-testify-in-blake-lively-justin-baldoni-case/news/",
    "source": "Stereogum",
    "published": "Fri, 12 Sep 2025 15:48:49 +0000",
    "image": null
  },
  {
    "title": "Anna Of The North \u2013 \u201cWaiting For Love\u201d",
    "link": "https://www.stereogum.com/2322786/anna-of-the-north-waiting-for-love/music/",
    "source": "Stereogum",
    "published": "Fri, 12 Sep 2025 15:47:17 +0000",
    "image": null
  },
  {
    "title": "Chris Cornell\u2019s Daughter Toni Cornell Unveils New Song \u201cCampari\u201d: Stream",
    "link": "https://consequence.net/2025/09/toni-cornell-new-song-campari/",
    "source": "Consequence",
    "published": "Fri, 12 Sep 2025 15:45:41 +0000",
    "image": "https://consequence.net/wp-content/uploads/2025/09/Toni-Cornell.jpg?quality=80"
  },
  {
    "title": "Foo Fighters To Return With Surprise California Show",
    "link": "https://www.spin.com/2025/09/foo-fighters-surprise-california-show/",
    "source": "SPIN",
    "published": "Fri, 12 Sep 2025 15:38:00 +0000",
    "image": "https://static.spin.com/files/2025/01/GettyImages-2196894108-scaled.jpg"
  },
  {
    "title": "Ego Nwodim Leaving SNL After Seven Seasons",
    "link": "https://consequence.net/2025/09/ego-nwodim-leaving-snl/",
    "source": "Consequence",
    "published": "Fri, 12 Sep 2025 15:30:50 +0000",
    "image": "https://consequence.net/wp-content/uploads/2025/09/ego-nwodim-snl.jpg?quality=80"
  },
  {
    "title": "Mobb Deep Return with First Posthumous Single \u201cAgainst the World\u201d: Stream",
    "link": "https://consequence.net/2025/09/mobb-deep-posthumous-single-against-the-world/",
    "source": "Consequence",
    "published": "Fri, 12 Sep 2025 15:10:52 +0000",
    "image": "https://consequence.net/wp-content/uploads/2025/09/mobb-deep-against-the-world-posthumous-single.jpg?quality=80"
  },
  {
    "title": "Scooby-Doo Dropped An Album Of Lofi Hip-Hop Radio Beats To Relax/Study To",
    "link": "https://www.stereogum.com/2322795/scooby-doo-dropped-an-album-of-lofi-hip-hop-radio-beats-to-relax-study-to/music/",
    "source": "Stereogum",
    "published": "Fri, 12 Sep 2025 15:07:46 +0000",
    "image": null
  },
  {
    "title": "Pink Floyd celebrate \u2018Wish You Were Here\u2019 50th anniversary with new box set: hear \u201cThe Machine Song\u201d demo",
    "link": "https://www.brooklynvegan.com/pink-floyd-celebrate-wish-you-were-here-50th-anniversary-with-new-box-set-hear-the-machine-song-demo/",
    "source": "BrooklynVegan",
    "published": "Fri, 12 Sep 2025 14:56:17 +0000",
    "image": null
  },
  {
    "title": "Spinal Tap Release The End Continues Album Featuring Paul McCartney and Elton John: Stream",
    "link": "https://consequence.net/2025/09/spinal-tap-the-end-continues-album-stream/",
    "source": "Consequence",
    "published": "Fri, 12 Sep 2025 14:55:20 +0000",
    "image": "https://consequence.net/wp-content/uploads/2025/09/Spinal-Tap-photo-by-Henry-Diltz.jpeg?quality=80"
  },
  {
    "title": "Mobb Deep Announce New Album Infinite, Share New Song \u201cAgainst the World\u201d: Listen",
    "link": "https://pitchfork.com/news/mobb-deep-announce-new-album-infinite-share-new-song-against-the-world-listen",
    "source": "RSS: News",
    "published": "Fri, 12 Sep 2025 14:49:31 +0000",
    "image": "https://media.pitchfork.com/photos/68c4323c21dcd785d28f3928/master/pass/Mobb-Deep.jpeg"
  },
  {
    "title": "Smashing Pumpkins \u2013 \u201cChrome Jets\u201d",
    "link": "https://www.stereogum.com/2322789/smashing-pumpkins-chrome-jets/music/",
    "source": "Stereogum",
    "published": "Fri, 12 Sep 2025 14:47:55 +0000",
    "image": null
  },
  {
    "title": "Pink Floyd Announce Wish You Were Here 50th Anniversary Reissue, Share \u201cWelcome to the Machine\u201d Demo: Listen",
    "link": "https://pitchfork.com/news/pink-floyd-announce-wish-you-were-here-50th-anniversary-reissue-share-welcome-to-the-machine-demo-listen",
    "source": "RSS: News",
    "published": "Fri, 12 Sep 2025 14:34:29 +0000",
    "image": "https://media.pitchfork.com/photos/68c32a754988cc757b1cd62f/master/pass/Pink-Floyd.jpeg"
  },
  {
    "title": "Madison Cunningham \u2013 \u201cWake\u201d (Feat. Fleet Foxes)",
    "link": "https://www.stereogum.com/2322772/madison-cunningham-wake-feat-fleet-foxes/music/",
    "source": "Stereogum",
    "published": "Fri, 12 Sep 2025 14:32:34 +0000",
    "image": null
  },
  {
    "title": "Weezer Had Another Fall Festival Cancel On Them",
    "link": "https://www.stereogum.com/2322769/weezer-had-another-fall-festival-cancel-on-them/news/",
    "source": "Stereogum",
    "published": "Fri, 12 Sep 2025 14:29:53 +0000",
    "image": null
  },
  {
    "title": "Listen to Madison Cunningham and Fleet Foxes\u2019 New Song \u201cWake\u201d",
    "link": "https://pitchfork.com/news/listen-to-madison-cunningham-and-fleet-foxes-new-song-wake",
    "source": "RSS: News",
    "published": "Fri, 12 Sep 2025 14:22:35 +0000",
    "image": "https://media.pitchfork.com/photos/68c3020a40b71cca385eb449/master/pass/Madison-Cunningham-Fleet-Foxes-Robin-Pecknold.jpg"
  },
  {
    "title": "Stereolab share new 7\u2033 (listen); North American tour starts this weekend",
    "link": "https://www.brooklynvegan.com/stereolab-share-new-7-listen-north-american-tour-starts-this-weekend/",
    "source": "BrooklynVegan",
    "published": "Fri, 12 Sep 2025 14:04:37 +0000",
    "image": null
  },
  {
    "title": "5 Albums I Can\u2019t Live Without: Se\u00e1n Griffin of the Ruffians",
    "link": "https://www.spin.com/2025/09/5-albums-i-cant-live-without-sean-griffin-of-the-ruffians/",
    "source": "SPIN",
    "published": "Fri, 12 Sep 2025 14:00:00 +0000",
    "image": "https://static.spin.com/files/2025/09/Sean-Griffin-Final-21.jpg"
  },
  {
    "title": "Mac DeMarco Did Not Crank Up The BPMs On Colbert, And That\u2019s OK",
    "link": "https://www.stereogum.com/2322763/mac-demarco-did-not-crank-up-the-bpms-on-colbert-and-thats-ok/news/",
    "source": "Stereogum",
    "published": "Fri, 12 Sep 2025 13:53:59 +0000",
    "image": null
  },
  {
    "title": "Pink Floyd Look Back On \u2018Wish You Were Here\u2019",
    "link": "https://www.spin.com/2025/09/pink-floyd-wish-you-were-here-reissue/",
    "source": "SPIN",
    "published": "Fri, 12 Sep 2025 13:51:22 +0000",
    "image": "https://static.spin.com/files/2025/09/Pink-Floyd-WYWH50-Credit-Storm-Thorgerson-Sony-Music-Entertainment.jpg"
  },
  {
    "title": "Limp Bizkit Made A Song Called \u201cMaking Love To Morgan Wallen\u201d",
    "link": "https://www.stereogum.com/2322762/limp-bizkit-made-a-song-called-makin-love-to-morgan-wallen/music/",
    "source": "Stereogum",
    "published": "Fri, 12 Sep 2025 13:49:56 +0000",
    "image": null
  },
  {
    "title": "Notable Releases of the Week (9/12)",
    "link": "https://www.brooklynvegan.com/maruja-algernon-cadwallader-saturdays-at-your-place-the-sound-of-animals-fighting-kassa-overall-restraining-order-die-spitz-iron-wine-ben-bridwell-reviews/",
    "source": "BrooklynVegan",
    "published": "Fri, 12 Sep 2025 13:49:39 +0000",
    "image": null
  },
  {
    "title": "LCD Soundystem Ready Annual NYC Residency",
    "link": "https://www.spin.com/2025/09/lcd-soundystem-new-york-residency/",
    "source": "SPIN",
    "published": "Fri, 12 Sep 2025 13:45:00 +0000",
    "image": null
  },
  {
    "title": "Indie Basement (9/12): the week in classic indie, alternative & college rock",
    "link": "https://www.brooklynvegan.com/album-reviews-the-chameleons-gruff-rhys-baxter-dury-guerilla-toss-sidney-minsky-sargeant-the-hidden-cameras-cosmic-rough-riders/",
    "source": "BrooklynVegan",
    "published": "Fri, 12 Sep 2025 13:38:31 +0000",
    "image": null
  },
  {
    "title": "Surprise: Djo Delivers Second New LP In Five Months",
    "link": "https://www.spin.com/2025/09/djo-new-album/",
    "source": "SPIN",
    "published": "Fri, 12 Sep 2025 13:32:00 +0000",
    "image": "https://static.spin.com/files/2025/01/Screen-Shot-2025-01-24-at-12.47.53-AM.png"
  },
  {
    "title": "Deep Cut Friday: \u2018It\u2019s a Jungle Out There\u2019 by Harry Nilsson",
    "link": "https://www.spin.com/2025/09/deep-cut-friday-its-a-jungle-out-there-by-harry-nilsson/",
    "source": "SPIN",
    "published": "Fri, 12 Sep 2025 13:30:00 +0000",
    "image": "https://static.spin.com/files/2025/08/GettyImages-706853485.jpg"
  },
  {
    "title": "Pink Floyd\u2019s Wish You Were Here Came Out 50 Years Ago Today: Hear A Previously Unreleased Demo From The New Box Set",
    "link": "https://www.stereogum.com/2322753/pink-floyds-wish-you-were-here-came-out-50-years-ago-today-hear-a-previously-unreleased-demo-from-the-new-box-set/music/",
    "source": "Stereogum",
    "published": "Fri, 12 Sep 2025 13:27:56 +0000",
    "image": null
  },
  {
    "title": "Yumi Zouma Announce New Album No Love Lost To Kindness: Hear \u201cDrag\u201d",
    "link": "https://www.stereogum.com/2322647/yumi-zouma-announce-new-album-no-lost-love-to-kindness-hear-drag/music/",
    "source": "Stereogum",
    "published": "Fri, 12 Sep 2025 13:24:04 +0000",
    "image": null
  },
  {
    "title": "Watch Mac DeMarco Perform \u201cShining\u201d on Colbert",
    "link": "https://pitchfork.com/news/watch-mac-demarco-perform-shining-on-colbert",
    "source": "RSS: News",
    "published": "Fri, 12 Sep 2025 13:24:00 +0000",
    "image": "https://media.pitchfork.com/photos/68c410fdbf6ccfab840d3deb/master/pass/mac%20demarco%20colbert.jpg"
  },
  {
    "title": "Stereolab \u2013 \u201cFed Up With Your Job\u201d & \u201cConstant And Uniform Movement Unknown\u201d",
    "link": "https://www.stereogum.com/2322725/stereolab-fed-up-with-your-job-constant-and-uniform-movement-unknown/music/",
    "source": "Stereogum",
    "published": "Fri, 12 Sep 2025 13:12:58 +0000",
    "image": null
  },
  {
    "title": "Algernon Cadwallader Aren\u2019t Overthinking This",
    "link": "https://www.stereogum.com/2318811/algernon-cadwallader-reunion-album-peter-helmis-joe-reinhart/interviews/qa/",
    "source": "Stereogum",
    "published": "Fri, 12 Sep 2025 13:01:56 +0000",
    "image": null
  },
  {
    "title": "13 New Albums You Should Listen to Now: Jade, Algernon Cadwallader, Jens Lekman, and More",
    "link": "https://pitchfork.com/news/13-new-albums-you-should-listen-to-now-jade-algernon-cadwallader-jens-lekman",
    "source": "RSS: News",
    "published": "Fri, 12 Sep 2025 13:01:44 +0000",
    "image": "https://media.pitchfork.com/photos/68c0733c98c6b54a2925d529/master/pass/JADE.jpeg"
  },
  {
    "title": "The Pretty Things Drummer Viv Prince Dead At 84",
    "link": "https://www.stereogum.com/2322750/the-pretty-things-drummer-viv-prince-dead-at-84/news/",
    "source": "Stereogum",
    "published": "Fri, 12 Sep 2025 12:48:16 +0000",
    "image": null
  },
  {
    "title": "LCD Soundsystem Announce 2025 New York Residency",
    "link": "https://pitchfork.com/news/lcd-soundsystem-announce-2025-new-york-residency",
    "source": "RSS: News",
    "published": "Fri, 12 Sep 2025 12:18:26 +0000",
    "image": "https://media.pitchfork.com/photos/68c3300af3d227bacdfcb799/master/pass/LCD-Soundsystem-James-Murphy-2025.jpeg"
  },
  {
    "title": "LCD Soundsystem announce 2025 NYC residency",
    "link": "https://www.brooklynvegan.com/lcd-soundsystem-announce-2025-nyc-residency/",
    "source": "BrooklynVegan",
    "published": "Fri, 12 Sep 2025 12:04:56 +0000",
    "image": null
  }
]